am/__init__.py
am/mysql_base.py
am/mysql_base_test.py
am/autogen/MySqlBaseLexer.interp
am/autogen/MySqlBaseLexer.py
am/autogen/MySqlBaseLexer.tokens
am/autogen/MySqlBaseParser.interp
am/autogen/MySqlBaseParser.py
am/autogen/MySqlBaseParser.tokens
am/autogen/MySqlBaseParserListener.py
am/autogen/MySqlBaseParserVisitor.py
am/autogen/__init__.py
antlr4_mysql-0.1.1.dist-info/LICENSE
antlr4_mysql-0.1.1.dist-info/METADATA
antlr4_mysql-0.1.1.dist-info/WHEEL
antlr4_mysql-0.1.1.dist-info/top_level.txt
antlr4_mysql-0.1.1.dist-info/RECORD
