Metadata-Version: 2.1
Name: antlr4-mysql
Version: 0.1.1
Summary: antlr4-mysql
Home-page: https://github.com/jsbxyyx/antlr4-mysql
Author: jsbxyyx
Author-email: jsbxyyx@163.com
License: Apache License 2.0
Platform: UNKNOWN
Classifier: Programming Language :: Python :: 3
Classifier: Operating System :: OS Independent
Requires-Dist: antlr4-python3-runtime (==4.9.2)
